fastdb4py-0.1.9.dist-info/WHEEL
fastdb4py-0.1.9.dist-info/top_level.txt
fastdb4py-0.1.9.dist-info/METADATA
fastdb4py-0.1.9.dist-info/RECORD
fastdb4py-0.1.9.dist-info/licenses/LICENSE
fastdb4py/type.py
fastdb4py/__init__.py
fastdb4py/orm/__init__.py
fastdb4py/orm/table.py
fastdb4py/feature/feature.py
fastdb4py/feature/utils.py
fastdb4py/feature/__init__.py
fastdb4py/feature/base.py
fastdb4py/core/_fastdb4py.so
fastdb4py/core/libfastdb.so
fastdb4py/core/libfastdb4py.so
fastdb4py/core/__init__.py
fastdb4py.libs/libfastdb-b40ce24e.so
