Metadata-Version: 2.4
Name: fastdb4py
Version: 0.1.9
Summary: FastCarto database bindings
Requires-Python: >=3.10
License-File: LICENSE
Requires-Dist: numpy
Dynamic: license-file
